gingerbread/__init__.py
gingerbread/_cffi_deps.py
gingerbread/_geometry.py
gingerbread/_print.py
gingerbread/_sexpr.py
gingerbread/_svg_document.py
gingerbread/_utils.py
gingerbread/convert.py
gingerbread/fancytext.py
gingerbread/pcb.py
gingerbread/py.typed
gingerbread/trace.py
gingerbread-2022.8.23.dist-info/LICENSE
gingerbread-2022.8.23.dist-info/WHEEL
gingerbread-2022.8.23.dist-info/METADATA
gingerbread-2022.8.23.dist-info/RECORD
