Metadata-Version: 2.1
Name: gingerbread
Version: 2022.8.23
Summary: Gingerbread is a set of Python utilities used by Winterbloom
Author-email: Alethea Katherine Flowers <thea@winterbloom.com>
Requires-Python: >=3.10
Classifier: License :: OSI Approved :: MIT License
Requires-Dist: cairosvg
Requires-Dist: cairocffi
Requires-Dist: pangocffi
Requires-Dist: pangocairocffi
Requires-Dist: potracecffi
Requires-Dist: svgpathtools
Requires-Dist: rich
Requires-Dist: defusedxml
Requires-Dist: cssselect2
Requires-Dist: pyperclip
Requires-Dist: numpy
Requires-Dist: pyvips
Requires-Dist: gdstk
Project-URL: Source, https://github.com/wntrblm/gingerbread
